packserver/__init__.py
packserver/__main__.py
packserver-1.1.0.dist-info/METADATA
packserver-1.1.0.dist-info/WHEEL
packserver-1.1.0.dist-info/entry_points.txt
packserver-1.1.0.dist-info/RECORD
